joseph/__init__.py
joseph/data.py
joseph/io.py
joseph/trade.py
joseph/utils.py
joseph-0.0.3.dist-info/METADATA
joseph-0.0.3.dist-info/WHEEL
joseph-0.0.3.dist-info/top_level.txt
joseph-0.0.3.dist-info/RECORD
